tests
trashtalk
