Metadata-Version: 1.1
Name: trashtalk
Version: 0.0.6
Summary: simplify trash in command line
Home-page: https://github.com/PTank/trashtalk
Author: PTank
Author-email: akazian@student.42.fr
License: UNKNOWN
Platform: UNKNOWN
Classifier: Programming Language :: Python
Classifier: License :: OSI Approved :: MIT License
Classifier: Natural Language :: English
Classifier: Operating System :: POSIX
Classifier: Programming Language :: Python :: 3
Classifier: Programming Language :: Python :: 2
Classifier: Topic :: Utilities
